statanalysis/__init__.py
statanalysis/common.py
statanalysis/conf_inte_md/__init__.py
statanalysis/conf_inte_md/ci_estimators.py
statanalysis/conf_inte_md/confidence_interval.py
statanalysis/hyp_testi_md/__init__.py
statanalysis/hyp_testi_md/hp_estimators.py
statanalysis/hyp_testi_md/hypothesis_testing.py
statanalysis/hyp_vali_md/__init__.py
statanalysis/hyp_vali_md/constraints.py
statanalysis/hyp_vali_md/hypothesis_validator.py
statanalysis/mdl_esti_md/__init__.py
statanalysis/mdl_esti_md/hp_estimators_regression.py
statanalysis/mdl_esti_md/log_reg_example.py
statanalysis/mdl_esti_md/model_estimator.py
statanalysis/mdl_esti_md/prediction_metrics.py
statanalysis/mdl_esti_md/prediction_results.py
statanalysis/utils_md/__init__.py
statanalysis/utils_md/compute_ppf_and_p_value.py
statanalysis/utils_md/constants.py
statanalysis/utils_md/estimate_std.py
statanalysis/utils_md/preprocessing.py
statanalysis/utils_md/refactoring.py
stat_analysis-1.0.0.dist-info/LICENSE
stat_analysis-1.0.0.dist-info/METADATA
stat_analysis-1.0.0.dist-info/WHEEL
stat_analysis-1.0.0.dist-info/RECORD
