Metadata-Version: 2.1
Name: stat-analysis
Version: 1.0.0
Summary: A Python library providing hands on implementation of a collection of common statistical methods for data analysis.
Home-page: https://github.com/Hermann-web/some-common-statistical-methods
License: Apache License
Keywords: statistics,data analysis,confidence intervals,hypothesis testing,model estimation,regression,statistical learning
Author: Hermann Agossou
Author-email: agossouhermann7@gmail.com
Maintainer: Hermann Agossou
Maintainer-email: agossouhermann7@gmail.com
Requires-Python: >=3.9,<4.0
Classifier: Development Status :: 5 - Production/Stable
Classifier: Intended Audience :: Science/Research
Classifier: License :: OSI Approved :: Apache Software License
Classifier: License :: Other/Proprietary License
Classifier: Operating System :: OS Independent
Classifier: Programming Language :: Python :: 3
Classifier: Programming Language :: Python :: 3.9
Classifier: Programming Language :: Python :: 3.10
Classifier: Programming Language :: Python :: 3.11
Classifier: Programming Language :: Python :: 3.12
Classifier: Topic :: Scientific/Engineering :: Mathematics
Classifier: Topic :: Software Development :: Libraries :: Python Modules
Requires-Dist: numpy (>=1.14.0,<2.0.0)
Requires-Dist: scipy (>=1.8.0,<2.0.0)
Requires-Dist: statsmodels (>=0.14.0,<0.15.0)
Project-URL: Documentation, https://github.com/Hermann-web/some-common-statistical-methods/blob/main/docs/detailled-docu.md
Project-URL: Repository, https://github.com/Hermann-web/some-common-statistical-methods
